Metadata-Version: 2.1
Name: rabbitmq-tool
Version: 0.0.1
Summary: A RabbitMQ CLI
Home-page: https://github.com/nvllsvm/rabbitmq-tool
Author: Andrew Rabert
Author-email: ar@nullsum.net
License: MIT
Platform: UNKNOWN
Classifier: License :: OSI Approved :: MIT License
Classifier: Programming Language :: Python :: 3
Classifier: Programming Language :: Python :: 3.9
